jaxtoolz/__init__.py
jaxtoolz/rand.py
jaxtoolz/sort.py
jaxtoolz/sorting.py
jaxtoolz-0.0.3.dist-info/METADATA
jaxtoolz-0.0.3.dist-info/WHEEL
jaxtoolz-0.0.3.dist-info/top_level.txt
jaxtoolz-0.0.3.dist-info/RECORD
