Metadata-Version: 2.1
Name: jaxtoolz
Version: 0.0.3
Summary: Jack's Tools
Home-page: UNKNOWN
Author: jingus
Author-email: <dev.jingus@protonmail.com>
License: UNKNOWN
Keywords: python,jaxtoolz,jackstools
Platform: UNKNOWN
Classifier: Development Status :: 1 - Planning
Classifier: Intended Audience :: End Users/Desktop
Classifier: Programming Language :: Python :: 3
Classifier: Operating System :: Microsoft :: Windows
